Metadata-Version: 2.4
Name: mcp-upstage
Version: 0.3.0
Summary: An MCP server for Upstage document parsing and information extraction
Project-URL: Homepage, https://github.com/UpstageAI/mcp-server-upstage
Project-URL: Issues, https://github.com/UpstageAI/mcp-server-upstage/issues
Project-URL: Repository, https://github.com/UpstageAI/mcp-server-upstage
License: MIT
License-File: LICENSE
Classifier: Development Status :: 4 - Beta
Classifier: Intended Audience :: Developers
Classifier: License :: OSI Approved :: MIT License
Classifier: Operating System :: OS Independent
Classifier: Programming Language :: Python :: 3
Classifier: Programming Language :: Python :: 3.10
Classifier: Programming Language :: Python :: 3.11
Classifier: Programming Language :: Python :: 3.12
Requires-Python: >=3.10
Requires-Dist: aiofiles>=24.1.0
Requires-Dist: httpx>=0.24.0
Requires-Dist: mcp[cli]>=1.6.0
Requires-Dist: python-dotenv>=1.0.0
Requires-Dist: tenacity>=9.1.2
Provides-Extra: dev
Requires-Dist: pytest-asyncio>=0.21.0; extra == 'dev'
Requires-Dist: pytest-cov>=4.1.0; extra == 'dev'
Requires-Dist: pytest>=7.0.0; extra == 'dev'
